[
    {
        "hero_name": "Medusa",
        "disadvantage_percentage": "5.11%",
        "win_rate": "35.69%",
        "matches": "13,862"
    },
    {
        "hero_name": "Bristleback",
        "disadvantage_percentage": "3.68%",
        "win_rate": "41.90%",
        "matches": "12,884"
    },
    {
        "hero_name": "Sand King",
        "disadvantage_percentage": "3.04%",
        "win_rate": "39.97%",
        "matches": "17,889"
    },
    {
        "hero_name": "Chen",
        "disadvantage_percentage": "2.82%",
        "win_rate": "48.85%",
        "matches": "739"
    },
    {
        "hero_name": "Snapfire",
        "disadvantage_percentage": "2.54%",
        "win_rate": "47.01%",
        "matches": "10,087"
    },
    {
        "hero_name": "Warlock",
        "disadvantage_percentage": "2.49%",
        "win_rate": "38.20%",
        "matches": "13,451"
    },
    {
        "hero_name": "Ember Spirit",
        "disadvantage_percentage": "2.33%",
        "win_rate": "44.04%",
        "matches": "16,203"
    },
    {
        "hero_name": "Dawnbreaker",
        "disadvantage_percentage": "2.22%",
        "win_rate": "43.08%",
        "matches": "6,251"
    },
    {
        "hero_name": "Viper",
        "disadvantage_percentage": "2.00%",
        "win_rate": "43.07%",
        "matches": "12,166"
    },
    {
        "hero_name": "Windranger",
        "disadvantage_percentage": "1.90%",
        "win_rate": "43.66%",
        "matches": "26,407"
    },
    {
        "hero_name": "Kunkka",
        "disadvantage_percentage": "1.85%",
        "win_rate": "41.76%",
        "matches": "10,904"
    },
    {
        "hero_name": "Lina",
        "disadvantage_percentage": "1.76%",
        "win_rate": "44.55%",
        "matches": "28,748"
    },
    {
        "hero_name": "Lich",
        "disadvantage_percentage": "1.65%",
        "win_rate": "40.29%",
        "matches": "15,854"
    },
    {
        "hero_name": "Witch Doctor",
        "disadvantage_percentage": "1.61%",
        "win_rate": "41.23%",
        "matches": "25,939"
    },
    {
        "hero_name": "Earthshaker",
        "disadvantage_percentage": "1.55%",
        "win_rate": "44.31%",
        "matches": "26,002"
    },
    {
        "hero_name": "Sniper",
        "disadvantage_percentage": "1.49%",
        "win_rate": "44.24%",
        "matches": "31,446"
    },
    {
        "hero_name": "Rubick",
        "disadvantage_percentage": "1.49%",
        "win_rate": "46.31%",
        "matches": "33,648"
    },
    {
        "hero_name": "Troll Warlord",
        "disadvantage_percentage": "1.48%",
        "win_rate": "43.47%",
        "matches": "7,829"
    },
    {
        "hero_name": "Jakiro",
        "disadvantage_percentage": "1.40%",
        "win_rate": "43.51%",
        "matches": "24,829"
    },
    {
        "hero_name": "Clinkz",
        "disadvantage_percentage": "1.38%",
        "win_rate": "42.86%",
        "matches": "9,071"
    },
    {
        "hero_name": "Dazzle",
        "disadvantage_percentage": "1.12%",
        "win_rate": "46.27%",
        "matches": "13,494"
    },
    {
        "hero_name": "Shadow Fiend",
        "disadvantage_percentage": "1.08%",
        "win_rate": "45.73%",
        "matches": "29,380"
    },
    {
        "hero_name": "Undying",
        "disadvantage_percentage": "1.08%",
        "win_rate": "41.88%",
        "matches": "11,517"
    },
    {
        "hero_name": "Drow Ranger",
        "disadvantage_percentage": "1.07%",
        "win_rate": "44.61%",
        "matches": "16,986"
    },
    {
        "hero_name": "Crystal Maiden",
        "disadvantage_percentage": "1.02%",
        "win_rate": "44.19%",
        "matches": "19,593"
    },
    {
        "hero_name": "Huskar",
        "disadvantage_percentage": "0.92%",
        "win_rate": "46.17%",
        "matches": "8,332"
    },
    {
        "hero_name": "Abaddon",
        "disadvantage_percentage": "0.87%",
        "win_rate": "38.60%",
        "matches": "12,190"
    },
    {
        "hero_name": "Primal Beast",
        "disadvantage_percentage": "0.85%",
        "win_rate": "46.22%",
        "matches": "9,102"
    },
    {
        "hero_name": "Alchemist",
        "disadvantage_percentage": "0.76%",
        "win_rate": "44.25%",
        "matches": "9,204"
    },
    {
        "hero_name": "Batrider",
        "disadvantage_percentage": "0.74%",
        "win_rate": "51.53%",
        "matches": "2,455"
    },
    {
        "hero_name": "Treant Protector",
        "disadvantage_percentage": "0.73%",
        "win_rate": "42.43%",
        "matches": "10,019"
    },
    {
        "hero_name": "Phantom Assassin",
        "disadvantage_percentage": "0.70%",
        "win_rate": "43.42%",
        "matches": "36,547"
    },
    {
        "hero_name": "Enchantress",
        "disadvantage_percentage": "0.68%",
        "win_rate": "46.29%",
        "matches": "5,640"
    },
    {
        "hero_name": "Brewmaster",
        "disadvantage_percentage": "0.65%",
        "win_rate": "45.12%",
        "matches": "1,833"
    },
    {
        "hero_name": "Weaver",
        "disadvantage_percentage": "0.62%",
        "win_rate": "44.47%",
        "matches": "16,514"
    },
    {
        "hero_name": "Sven",
        "disadvantage_percentage": "0.55%",
        "win_rate": "46.65%",
        "matches": "9,984"
    },
    {
        "hero_name": "Techies",
        "disadvantage_percentage": "0.54%",
        "win_rate": "47.31%",
        "matches": "13,375"
    },
    {
        "hero_name": "Pangolier",
        "disadvantage_percentage": "0.53%",
        "win_rate": "48.32%",
        "matches": "5,660"
    },
    {
        "hero_name": "Winter Wyvern",
        "disadvantage_percentage": "0.52%",
        "win_rate": "44.77%",
        "matches": "5,732"
    },
    {
        "hero_name": "Slark",
        "disadvantage_percentage": "0.48%",
        "win_rate": "45.04%",
        "matches": "17,859"
    },
    {
        "hero_name": "Gyrocopter",
        "disadvantage_percentage": "0.47%",
        "win_rate": "47.41%",
        "matches": "8,334"
    },
    {
        "hero_name": "Phoenix",
        "disadvantage_percentage": "0.32%",
        "win_rate": "45.35%",
        "matches": "10,680"
    },
    {
        "hero_name": "Elder Titan",
        "disadvantage_percentage": "0.32%",
        "win_rate": "44.54%",
        "matches": "3,303"
    },
    {
        "hero_name": "Hoodwink",
        "disadvantage_percentage": "0.32%",
        "win_rate": "48.06%",
        "matches": "22,802"
    },
    {
        "hero_name": "Ringmaster",
        "disadvantage_percentage": "0.28%",
        "win_rate": "43.25%",
        "matches": "31,959"
    },
    {
        "hero_name": "Shadow Demon",
        "disadvantage_percentage": "0.27%",
        "win_rate": "46.05%",
        "matches": "5,257"
    },
    {
        "hero_name": "Queen of Pain",
        "disadvantage_percentage": "0.22%",
        "win_rate": "44.93%",
        "matches": "23,197"
    },
    {
        "hero_name": "Magnus",
        "disadvantage_percentage": "0.20%",
        "win_rate": "47.17%",
        "matches": "12,143"
    },
    {
        "hero_name": "Legion Commander",
        "disadvantage_percentage": "0.18%",
        "win_rate": "42.44%",
        "matches": "28,929"
    },
    {
        "hero_name": "Razor",
        "disadvantage_percentage": "0.15%",
        "win_rate": "44.09%",
        "matches": "10,770"
    },
    {
        "hero_name": "Tinker",
        "disadvantage_percentage": "0.11%",
        "win_rate": "42.15%",
        "matches": "10,794"
    },
    {
        "hero_name": "Marci",
        "disadvantage_percentage": "0.10%",
        "win_rate": "45.10%",
        "matches": "10,809"
    },
    {
        "hero_name": "Tiny",
        "disadvantage_percentage": "0.08%",
        "win_rate": "47.61%",
        "matches": "14,829"
    },
    {
        "hero_name": "Venomancer",
        "disadvantage_percentage": "0.07%",
        "win_rate": "47.75%",
        "matches": "14,709"
    },
    {
        "hero_name": "Dark Seer",
        "disadvantage_percentage": "0.07%",
        "win_rate": "44.54%",
        "matches": "5,496"
    },
    {
        "hero_name": "Meepo",
        "disadvantage_percentage": "0.03%",
        "win_rate": "46.17%",
        "matches": "2,714"
    },
    {
        "hero_name": "Io",
        "disadvantage_percentage": "0.03%",
        "win_rate": "45.02%",
        "matches": "6,086"
    },
    {
        "hero_name": "Tusk",
        "disadvantage_percentage": "0.02%",
        "win_rate": "49.62%",
        "matches": "7,771"
    },
    {
        "hero_name": "Leshrac",
        "disadvantage_percentage": "0.01%",
        "win_rate": "45.55%",
        "matches": "6,828"
    },
    {
        "hero_name": "Doom",
        "disadvantage_percentage": "-0.03%",
        "win_rate": "48.31%",
        "matches": "7,819"
    },
    {
        "hero_name": "Luna",
        "disadvantage_percentage": "-0.05%",
        "win_rate": "44.66%",
        "matches": "15,172"
    },
    {
        "hero_name": "Chaos Knight",
        "disadvantage_percentage": "-0.08%",
        "win_rate": "45.48%",
        "matches": "9,676"
    },
    {
        "hero_name": "Monkey King",
        "disadvantage_percentage": "-0.09%",
        "win_rate": "50.74%",
        "matches": "15,340"
    },
    {
        "hero_name": "Silencer",
        "disadvantage_percentage": "-0.11%",
        "win_rate": "42.80%",
        "matches": "12,984"
    },
    {
        "hero_name": "Mirana",
        "disadvantage_percentage": "-0.15%",
        "win_rate": "48.63%",
        "matches": "17,098"
    },
    {
        "hero_name": "Ancient Apparition",
        "disadvantage_percentage": "-0.17%",
        "win_rate": "43.47%",
        "matches": "11,009"
    },
    {
        "hero_name": "Templar Assassin",
        "disadvantage_percentage": "-0.20%",
        "win_rate": "50.73%",
        "matches": "6,966"
    },
    {
        "hero_name": "Keeper of the Light",
        "disadvantage_percentage": "-0.21%",
        "win_rate": "48.63%",
        "matches": "4,228"
    },
    {
        "hero_name": "Underlord",
        "disadvantage_percentage": "-0.24%",
        "win_rate": "42.55%",
        "matches": "9,056"
    },
    {
        "hero_name": "Bounty Hunter",
        "disadvantage_percentage": "-0.25%",
        "win_rate": "44.68%",
        "matches": "10,607"
    },
    {
        "hero_name": "Mars",
        "disadvantage_percentage": "-0.27%",
        "win_rate": "48.00%",
        "matches": "11,861"
    },
    {
        "hero_name": "Slardar",
        "disadvantage_percentage": "-0.36%",
        "win_rate": "46.46%",
        "matches": "12,021"
    },
    {
        "hero_name": "Oracle",
        "disadvantage_percentage": "-0.38%",
        "win_rate": "42.65%",
        "matches": "7,430"
    },
    {
        "hero_name": "Shadow Shaman",
        "disadvantage_percentage": "-0.38%",
        "win_rate": "43.15%",
        "matches": "19,646"
    },
    {
        "hero_name": "Dark Willow",
        "disadvantage_percentage": "-0.38%",
        "win_rate": "46.35%",
        "matches": "9,795"
    },
    {
        "hero_name": "Storm Spirit",
        "disadvantage_percentage": "-0.40%",
        "win_rate": "45.39%",
        "matches": "11,913"
    },
    {
        "hero_name": "Grimstroke",
        "disadvantage_percentage": "-0.41%",
        "win_rate": "47.49%",
        "matches": "7,957"
    },
    {
        "hero_name": "Dragon Knight",
        "disadvantage_percentage": "-0.53%",
        "win_rate": "46.86%",
        "matches": "16,595"
    },
    {
        "hero_name": "Zeus",
        "disadvantage_percentage": "-0.54%",
        "win_rate": "45.47%",
        "matches": "20,367"
    },
    {
        "hero_name": "Nature's Prophet",
        "disadvantage_percentage": "-0.55%",
        "win_rate": "48.45%",
        "matches": "18,272"
    },
    {
        "hero_name": "Disruptor",
        "disadvantage_percentage": "-0.58%",
        "win_rate": "45.82%",
        "matches": "11,252"
    },
    {
        "hero_name": "Arc Warden",
        "disadvantage_percentage": "-0.59%",
        "win_rate": "42.70%",
        "matches": "6,408"
    },
    {
        "hero_name": "Juggernaut",
        "disadvantage_percentage": "-0.61%",
        "win_rate": "43.86%",
        "matches": "26,079"
    },
    {
        "hero_name": "Terrorblade",
        "disadvantage_percentage": "-0.67%",
        "win_rate": "50.17%",
        "matches": "4,531"
    },
    {
        "hero_name": "Centaur Warrunner",
        "disadvantage_percentage": "-0.69%",
        "win_rate": "43.76%",
        "matches": "14,401"
    },
    {
        "hero_name": "Death Prophet",
        "disadvantage_percentage": "-0.77%",
        "win_rate": "46.49%",
        "matches": "5,743"
    },
    {
        "hero_name": "Earth Spirit",
        "disadvantage_percentage": "-0.80%",
        "win_rate": "47.22%",
        "matches": "5,258"
    },
    {
        "hero_name": "Ursa",
        "disadvantage_percentage": "-0.81%",
        "win_rate": "46.78%",
        "matches": "18,107"
    },
    {
        "hero_name": "Faceless Void",
        "disadvantage_percentage": "-0.90%",
        "win_rate": "48.75%",
        "matches": "14,514"
    },
    {
        "hero_name": "Void Spirit",
        "disadvantage_percentage": "-0.98%",
        "win_rate": "44.17%",
        "matches": "8,519"
    },
    {
        "hero_name": "Pugna",
        "disadvantage_percentage": "-0.99%",
        "win_rate": "48.12%",
        "matches": "7,043"
    },
    {
        "hero_name": "Vengeful Spirit",
        "disadvantage_percentage": "-1.00%",
        "win_rate": "44.39%",
        "matches": "16,554"
    },
    {
        "hero_name": "Naga Siren",
        "disadvantage_percentage": "-1.02%",
        "win_rate": "48.93%",
        "matches": "3,885"
    },
    {
        "hero_name": "Axe",
        "disadvantage_percentage": "-1.06%",
        "win_rate": "43.57%",
        "matches": "32,100"
    },
    {
        "hero_name": "Timbersaw",
        "disadvantage_percentage": "-1.07%",
        "win_rate": "46.03%",
        "matches": "14,527"
    },
    {
        "hero_name": "Spirit Breaker",
        "disadvantage_percentage": "-1.15%",
        "win_rate": "46.03%",
        "matches": "19,333"
    },
    {
        "hero_name": "Enigma",
        "disadvantage_percentage": "-1.15%",
        "win_rate": "47.05%",
        "matches": "7,088"
    },
    {
        "hero_name": "Lifestealer",
        "disadvantage_percentage": "-1.19%",
        "win_rate": "45.96%",
        "matches": "10,939"
    },
    {
        "hero_name": "Wraith King",
        "disadvantage_percentage": "-1.23%",
        "win_rate": "40.66%",
        "matches": "22,620"
    },
    {
        "hero_name": "Visage",
        "disadvantage_percentage": "-1.32%",
        "win_rate": "45.01%",
        "matches": "4,930"
    },
    {
        "hero_name": "Invoker",
        "disadvantage_percentage": "-1.32%",
        "win_rate": "49.32%",
        "matches": "26,191"
    },
    {
        "hero_name": "Puck",
        "disadvantage_percentage": "-1.33%",
        "win_rate": "47.92%",
        "matches": "12,163"
    },
    {
        "hero_name": "Lion",
        "disadvantage_percentage": "-1.38%",
        "win_rate": "47.22%",
        "matches": "35,781"
    },
    {
        "hero_name": "Skywrath Mage",
        "disadvantage_percentage": "-1.38%",
        "win_rate": "45.27%",
        "matches": "12,378"
    },
    {
        "hero_name": "Ogre Magi",
        "disadvantage_percentage": "-1.61%",
        "win_rate": "45.57%",
        "matches": "25,348"
    },
    {
        "hero_name": "Tidehunter",
        "disadvantage_percentage": "-1.61%",
        "win_rate": "47.89%",
        "matches": "8,633"
    },
    {
        "hero_name": "Outworld Destroyer",
        "disadvantage_percentage": "-1.68%",
        "win_rate": "45.00%",
        "matches": "9,835"
    },
    {
        "hero_name": "Muerta",
        "disadvantage_percentage": "-1.73%",
        "win_rate": "49.15%",
        "matches": "4,494"
    },
    {
        "hero_name": "Pudge",
        "disadvantage_percentage": "-1.76%",
        "win_rate": "45.94%",
        "matches": "48,072"
    },
    {
        "hero_name": "Morphling",
        "disadvantage_percentage": "-1.78%",
        "win_rate": "52.63%",
        "matches": "10,432"
    },
    {
        "hero_name": "Necrophos",
        "disadvantage_percentage": "-1.87%",
        "win_rate": "44.56%",
        "matches": "15,831"
    },
    {
        "hero_name": "Broodmother",
        "disadvantage_percentage": "-1.92%",
        "win_rate": "46.74%",
        "matches": "6,016"
    },
    {
        "hero_name": "Lycan",
        "disadvantage_percentage": "-1.97%",
        "win_rate": "46.73%",
        "matches": "4,327"
    },
    {
        "hero_name": "Omniknight",
        "disadvantage_percentage": "-2.06%",
        "win_rate": "43.83%",
        "matches": "9,910"
    },
    {
        "hero_name": "Bane",
        "disadvantage_percentage": "-2.24%",
        "win_rate": "47.98%",
        "matches": "5,308"
    },
    {
        "hero_name": "Anti-Mage",
        "disadvantage_percentage": "-2.27%",
        "win_rate": "47.91%",
        "matches": "19,301"
    },
    {
        "hero_name": "Nyx Assassin",
        "disadvantage_percentage": "-2.33%",
        "win_rate": "46.59%",
        "matches": "15,438"
    },
    {
        "hero_name": "Riki",
        "disadvantage_percentage": "-2.33%",
        "win_rate": "45.83%",
        "matches": "8,295"
    },
    {
        "hero_name": "Lone Druid",
        "disadvantage_percentage": "-2.38%",
        "win_rate": "46.15%",
        "matches": "4,139"
    },
    {
        "hero_name": "Bloodseeker",
        "disadvantage_percentage": "-2.88%",
        "win_rate": "46.39%",
        "matches": "6,665"
    },
    {
        "hero_name": "Clockwerk",
        "disadvantage_percentage": "-3.05%",
        "win_rate": "46.36%",
        "matches": "9,056"
    },
    {
        "hero_name": "Spectre",
        "disadvantage_percentage": "-3.30%",
        "win_rate": "47.79%",
        "matches": "12,099"
    },
    {
        "hero_name": "Night Stalker",
        "disadvantage_percentage": "-3.35%",
        "win_rate": "45.79%",
        "matches": "9,968"
    },
    {
        "hero_name": "Phantom Lancer",
        "disadvantage_percentage": "-4.24%",
        "win_rate": "53.24%",
        "matches": "7,291"
    }
]